tj_hyd_tank/__init__.py
tj_hyd_tank/basin_def.py
tj_hyd_tank/tank_exception.py
tj_hyd_tank/tj_hyd_tank.py
tj_hyd_tank/tj_hyd_tank_utils.py
tj_hyd_tank-1.3.0.dist-info/METADATA
tj_hyd_tank-1.3.0.dist-info/WHEEL
tj_hyd_tank-1.3.0.dist-info/RECORD
