Metadata-Version: 2.1
Name: tj-hyd-tank
Version: 1.3.0
Summary: Python implementation of Tank Hydrological model by Sugawara and Funiyuki (1956)
Author: Duy Nguyen
Author-email: duynguyen02.dev@gmail.com
Requires-Python: >=3.9,<4.0
Classifier: Programming Language :: Python :: 3
Classifier: Programming Language :: Python :: 3.9
Classifier: Programming Language :: Python :: 3.10
Classifier: Programming Language :: Python :: 3.11
Classifier: Programming Language :: Python :: 3.12
Requires-Dist: matplotlib (>=3.9.2,<4.0.0)
Requires-Dist: pandas (>=2.2.2,<3.0.0)
Requires-Dist: spicy (>=0.16.0,<0.17.0)
